api/__init__.py
api/api.py
api/db.py
api/route.py
api/server.py
api/router/block.py
api/router/builder.py
api/router/cloudshell.py
api/router/compute.py
api/router/container.py
api/router/database.py
api/router/identity.py
api/router/image.py
api/router/message_queue.py
api/router/monitor.py
api/router/network.py
api/router/object_store.py
api/router/plan.py
api/static/index.html
api/static/assets/404.bbecdda0.png
api/static/assets/favicon.14927d17.ico
api/static/assets/index.966902b2.js
api/static/assets/index.f03e321a.css
api/static/assets/logo-splash.e281fcad.svg
backup/__init__.py
backup/db.py
backup/instance.py
backup/instance_backup.py
backup/instance_snapshot.py
backup/route.py
backup/server.py
backup/volume.py
backup/volume_backup.py
builder/__init__.py
builder/cluster.py
builder/db.py
builder/harbor.py
builder/harboradm
builder/k8s.py
builder/k8sadm
builder/kafka.py
builder/kafkaadm
builder/mariadb.py
builder/mariadbadm
builder/nfs.py
builder/nfsadm
builder/postgresql.py
builder/postgresqladm
builder/rabbitmq.py
builder/rabbitmqadm
builder/redis.py
builder/redisadm
builder/route.py
builder/server.py
builder/harbor-template/common.sh
builder/harbor-template/depot.repo.j2
builder/harbor-template/harbor.yml.j2
builder/harbor-template/hosts.j2
builder/harbor-template/install.sh
builder/harbor-template/prepare.j2
builder/k8s-template/bootstrap.yaml.j2
builder/k8s-template/cloud.conf.j2
builder/k8s-template/cloud.yaml.j2
builder/k8s-template/controller.ign.yaml.j2
builder/k8s-template/crictl.yaml
builder/k8s-template/crio.conf.j2
builder/k8s-template/depot.repo.j2
builder/k8s-template/hosts.j2
builder/k8s-template/join-controller.yaml.j2
builder/k8s-template/join-worker.yaml.j2
builder/k8s-template/kube-flannel.yaml.j2
builder/k8s-template/worker.ign.yaml.j2
builder/k8s-template/cloud-provider-openstack/cinder-csi-plugin/cinder-csi-controllerplugin-rbac.yaml
builder/k8s-template/cloud-provider-openstack/cinder-csi-plugin/cinder-csi-controllerplugin.yaml.j2
cloudms-20240509.0.dist-info/LICENSE
cloudms-20240509.0.dist-info/METADATA
cloudms-20240509.0.dist-info/WHEEL
cloudms-20240509.0.dist-info/top_level.txt
cloudms-20240509.0.dist-info/RECORD
